curricularanalytics/__init__.py
curricularanalytics/csv_utilities.py
curricularanalytics/data_handler.py
curricularanalytics/degree_plan_creation.py
curricularanalytics/graph_algs.py
curricularanalytics/py.typed
curricularanalytics/types/course.py
curricularanalytics/types/course_catalog.py
curricularanalytics/types/curriculum.py
curricularanalytics/types/data_types.py
curricularanalytics/types/degree_plan.py
curricularanalytics/types/degree_requirements.py
curricularanalytics/types/learning_outcome.py
curricularanalytics/types/simulation.py
curricularanalytics/types/student.py
curricularanalytics/types/student_record.py
curricularanalytics/types/transfer_articulation.py
curricularanalytics-0.2.0.dist-info/LICENSE.md
curricularanalytics-0.2.0.dist-info/METADATA
curricularanalytics-0.2.0.dist-info/WHEEL
curricularanalytics-0.2.0.dist-info/top_level.txt
curricularanalytics-0.2.0.dist-info/RECORD
