Metadata-Version: 2.1
Name: curricularanalytics
Version: 0.2.0
Summary: A toolbox for studying and analyzing academic program curricula.
Author-email: Sean Yen <seyen@ucsd.edu>, Greg Heileman <gregheileman@gmail.com>, Hayden Free <haydenwfree@gmail.com>, Orhan Abar <orhan.abar@uky.edu>, Will Thompson <wgthompson@uky.edu>
Classifier: Programming Language :: Python :: 3
Classifier: License :: OSI Approved :: GNU Affero General Public License v3
Classifier: Operating System :: OS Independent
Requires-Python: >=3.8
License-File: LICENSE.md
Requires-Dist: networkx >=3.1
Requires-Dist: pandas >=2.0.1
